README.md
setup.py
flask_clova/__about__.py
flask_clova/__init__.py
flask_clova/core.py
flask_clova/directives.py
flask_clova/models.py
flask_clova/speech.py
flask_clova/verifier.py
flask_clova.egg-info/PKG-INFO
flask_clova.egg-info/SOURCES.txt
flask_clova.egg-info/dependency_links.txt
flask_clova.egg-info/requires.txt
flask_clova.egg-info/top_level.txt