Metadata-Version: 1.1
Name: flask-clova
Version: 0.0.5
Summary: A Python Library For CEK
Home-page: https://github.com/hwonyo/flask-clova.git
Author: wonyoHwang
Author-email: hollal0726@gmail.com
License: MIT License
Keywords: CEK,clova,extension,clova-extension-kit
Platform: UNKNOWN
Classifier: Framework :: Flask
Classifier: Intended Audience :: Developers
Classifier: Environment :: Web Environment
Classifier: Programming Language :: Python :: 3
Classifier: License :: OSI Approved :: MIT License
